visibility_graph/__init__.py
visibility_graph-0.5.1.data/scripts/series2edgelist.py
visibility_graph-0.5.1.dist-info/LICENSE
visibility_graph-0.5.1.dist-info/METADATA
visibility_graph-0.5.1.dist-info/WHEEL
visibility_graph-0.5.1.dist-info/top_level.txt
visibility_graph-0.5.1.dist-info/RECORD
