Metadata-Version: 2.1
Name: visibility-graph
Version: 0.5.1
Summary: From time series to graph thru visibility algorithm.
Home-page: http://github.com/CSB-IG/visibility_graph
Author: Rodrigo Garcia
Author-email: Rodrigo Garcia-Herrera <rgarcia@riseup.net>
License: GPLv3
Project-URL: Homepage, http://github.com/CSB-IG/visibility_graph
Classifier: License :: OSI Approved :: GNU General Public License v3 (GPLv3)
Classifier: Topic :: Scientific/Engineering :: Information Analysis
Classifier: Intended Audience :: Science/Research
Classifier: Topic :: Scientific/Engineering
Requires-Python: >=3.7
License-File: LICENSE
Requires-Dist: networkx
